setup.py
cqplus/__init__.py
cqplus/_api.py
cqplus/_app.py
cqplus/_context.py
cqplus/_handler.py
cqplus/_logging.py
cqplus/_message.py
cqplus/six.py
cqplus_sdk.egg-info/PKG-INFO
cqplus_sdk.egg-info/SOURCES.txt
cqplus_sdk.egg-info/dependency_links.txt
cqplus_sdk.egg-info/top_level.txt