Metadata-Version: 2.1
Name: cqplus-sdk
Version: 1.0.6
Summary: coolq-sdk-x
Home-page: https://gitee.com/muxiaofei/coolq_sdk_x/wikis/pages
Author: Mu Xiaofei
Author-email: me@muxiaofei.cn
License: UNKNOWN
Keywords: 酷Q,coolq,cqplus,sdk
Platform: UNKNOWN
Classifier: Programming Language :: Python :: 2
Classifier: Programming Language :: Python :: 2.7
Classifier: Programming Language :: Python :: 3
Classifier: Programming Language :: Python :: 3.7
Classifier: License :: OSI Approved :: MIT License
Classifier: Operating System :: OS Independent
